file_watcher.py
User0092_File_Watcher-0.2.1.dist-info/LICENSE
User0092_File_Watcher-0.2.1.dist-info/METADATA
User0092_File_Watcher-0.2.1.dist-info/WHEEL
User0092_File_Watcher-0.2.1.dist-info/top_level.txt
User0092_File_Watcher-0.2.1.dist-info/RECORD
