Metadata-Version: 2.1
Name: User0092-File-Watcher
Version: 0.2.1
Summary: A simple package for monitoring new and updated files.
Author: User0092
Author-email: contact@user0092.online
License-File: LICENSE
